sharpcosine/__init__.py
sharpcosine/cos2d.py
sharpcosine/max_pool.py
sharpcosine-0.1.1.dist-info/METADATA
sharpcosine-0.1.1.dist-info/WHEEL
sharpcosine-0.1.1.dist-info/top_level.txt
sharpcosine-0.1.1.dist-info/RECORD
