Metadata-Version: 2.1
Name: sharpcosine
Version: 0.1.1
Author: TAWSIF AHMED
Author-email: sleeping4cat@outlook.com
Requires-Dist: tensorflow
Requires-Dist: numpy
